gat/__init__.py
gat/py.typed
gat/agents/__init__.py
gat/agents/agent.py
gat/agents/agent_config.py
gat/agents/agent_instructions.py
gat/agents/agent_run_response.py
gat/agents/models/__init__.py
gat/agents/models/context.py
gat/agents/pipelines/__init__.py
gat/agents/pipelines/agent_pipeline.py
gat/agents/squads/__init__.py
gat/agents/squads/agent_squad.py
gat/agents/tools/__init__..py
gat/agents/tools/agent_tool.py
gat/agents/tools/adapters/__init__.py
gat/generations/__init__.py
gat/generations/collections/__init__.py
gat/generations/collections/message_sequence.py
gat/generations/json/__init__.py
gat/generations/json/schema_builder.py
gat/generations/json/unsuported_type_error.py
gat/generations/models/__init__.py
gat/generations/models/assistant_message.py
gat/generations/models/audio_description.py
gat/generations/models/audio_element_description.py
gat/generations/models/audio_structure.py
gat/generations/models/audio_transcription.py
gat/generations/models/chain_of_thought.py
gat/generations/models/choice.py
gat/generations/models/developer_message.py
gat/generations/models/file_part.py
gat/generations/models/generated_assistant_message.py
gat/generations/models/generation.py
gat/generations/models/generation_config.py
gat/generations/models/graphical_element_description.py
gat/generations/models/media_structure.py
gat/generations/models/message.py
gat/generations/models/part.py
gat/generations/models/query_expansion.py
gat/generations/models/raw_parts_response.py
gat/generations/models/sentence_segment.py
gat/generations/models/step.py
gat/generations/models/text_part.py
gat/generations/models/thought_detail.py
gat/generations/models/tool_declaration_part.py
gat/generations/models/tool_execution_part.py
gat/generations/models/trace_params.py
gat/generations/models/usage.py
gat/generations/models/user_message.py
gat/generations/models/visual_media_description.py
gat/generations/pricing/__init__.py
global_agent_toolkit-0.0.15.dist-info/METADATA
global_agent_toolkit-0.0.15.dist-info/WHEEL
global_agent_toolkit-0.0.15.dist-info/RECORD
