Metadata-Version: 2.4
Name: global-agent-toolkit
Version: 0.0.15
Summary: ...
Author-email: Arthur Brenno <64020210+arthurbrenno@users.noreply.github.com>
Requires-Python: >=3.13
Requires-Dist: rock-solid-base>=0.0.12
